{
  "displayColumn": "name",
  "filterBuilder": "{\"condition\":\"AND\",\"rules\":[{\"andOr\":\"AND\",\"key\":\"pricetype\",\"operator\":\"=\",\"value\":null,\"name\":\"pricetype\",\"expression\":false,\"hidden\":false},{\"andOr\":\"\",\"key\":\"item\",\"operator\":\"contains\",\"value\":null,\"name\":\"item\",\"expression\":false,\"hidden\":false}]}",
  "isReactive": true,
  "meta": {
    "createdDate": {
      "displayName": "Created Date",
      "invisible": true,
      "order": 3,
      "type": "date"
    },
    "id": {
      "displayName": "id",
      "order": 8,
      "type": "number"
    },
    "internalid": {
      "displayName": "internalid",
      "order": 14,
      "type": "number"
    },
    "item": {
      "displayName": "item",
      "order": 9,
      "type": "number"
    },
    "itemquantityid": {
      "displayName": "itemquantityid",
      "order": 15,
      "type": "number"
    },
    "lastEditDate": {
      "displayName": "Last edit date",
      "invisible": true,
      "order": 7,
      "type": "date"
    },
    "lastEditedBy": {
      "displayName": "Last edited by",
      "invisible": true,
      "order": 6,
      "type": "user"
    },
    "layout": {
      "displayName": "Layout",
      "invisible": true,
      "order": 1,
      "type": "select"
    },
    "name": {
      "displayName": "Name",
      "order": 0,
      "type": "string"
    },
    "nextEvents": {
      "displayName": "Next Events",
      "invisible": true,
      "order": 5,
      "type": "string"
    },
    "owner": {
      "displayName": "Owner",
      "invisible": true,
      "order": 2,
      "type": "user"
    },
    "price": {
      "displayName": "price",
      "order": 10,
      "type": "number"
    },
    "pricetype": {
      "displayName": "pricetype",
      "indexed": true,
      "lookUpTable": "priceLevels",
      "order": 13,
      "type": "lookup"
    },
    "quantity": {
      "displayName": "quantity",
      "order": 12,
      "type": "number"
    },
    "state": {
      "displayName": "State",
      "invisible": true,
      "order": 4,
      "type": "string"
    },
    "version": {
      "displayName": "version",
      "order": 11,
      "type": "number"
    }
  },
  "rowEditorFieldsForm": {
    "sections": [
      {
        "name": "section_158941",
        "label": "",
        "clientKey": "section_158941",
        "order": 0,
        "rows": [
          {
            "name": "section_158941_row_137940",
            "label": "",
            "order": 0,
            "controls": [
              {
                "type": "text",
                "name": "control_4bd78222-3e3c-11f0-bc89-c5ab2e46fbcb",
                "fieldName": "control_4bd78222-3e3c-11f0-bc89-c5ab2e46fbcb",
                "label": "Name",
                "order": 0,
                "defaultValue": "",
                "value": "",
                "className": "col-md-6",
                "useWidthPercentages": false,
                "widthPercentages": null,
                "readonly": false,
                "readonlyCondition": "",
                "placeholder": "",
                "required": false,
                "requiredCondition": "",
                "isMultiLine": false,
                "isInteger": false,
                "decimalPlace": 2,
                "expression": "",
                "additionalFilter": "",
                "oneDriveFileId": null,
                "isTodayValue": false,
                "isTodayValueCreated": true,
                "dateFormat": "mm/dd/yy hh:mm p",
                "timezone": null,
                "selectedDataGrid": null,
                "printedFileName": null,
                "dataFetchDepth": "basic",
                "buttonLabel": "",
                "dataForTemplate": null,
                "selectedOutputDataGrid": null,
                "templateRowKey": null,
                "isForDownload": true,
                "isOneDriveTemplate": false,
                "selectedOneDriveFile": null,
                "openInNewTab": true,
                "attachRecord": false,
                "isCurrentUser": false,
                "isCurrentUserOwner": true,
                "isNowTimeValue": false,
                "timeFormat": "HH:mm",
                "isMultiple": false,
                "isAjax": false,
                "dataOptions": [],
                "ajaxDataUrl": "",
                "isChecked": false,
                "vif": "",
                "customCode": "",
                "invisible": false,
                "invisibleCondition": "",
                "invisibleLabel": false,
                "enableCustomValidation": false,
                "customValidationRule": "",
                "customValidationErrorMessage": "",
                "mask": "",
                "lookupOpenInModalDisabled": false,
                "preventModalShowUpWhenNewItemAdded": false,
                "lookUpSearch": null,
                "editorMode": "javascript",
                "dataGridAvailableViews": [],
                "dataGridView": null,
                "dataGridAddRecordsText": "",
                "dataGridAddRecordText": "",
                "skipCrop": false,
                "disableRoundedStyle": false,
                "attachedFunction": "",
                "buttonText": "",
                "buttonVariant": "primary",
                "customClassName": "",
                "propName": "name"
              },
              {
                "type": "number",
                "name": "control_9980cb80-3e3c-11f0-bc89-c5ab2e46fbcb",
                "fieldName": "control_9980cb80-3e3c-11f0-bc89-c5ab2e46fbcb",
                "label": "id",
                "order": 0,
                "defaultValue": "",
                "value": "",
                "className": "col-md-6",
                "useWidthPercentages": false,
                "widthPercentages": null,
                "readonly": false,
                "readonlyCondition": "",
                "placeholder": "",
                "required": false,
                "requiredCondition": "",
                "isMultiLine": false,
                "isInteger": false,
                "decimalPlace": 2,
                "expression": "",
                "additionalFilter": "",
                "oneDriveFileId": null,
                "isTodayValue": false,
                "isTodayValueCreated": true,
                "dateFormat": "mm/dd/yy hh:mm p",
                "timezone": null,
                "selectedDataGrid": null,
                "printedFileName": null,
                "dataFetchDepth": "basic",
                "buttonLabel": "",
                "dataForTemplate": null,
                "selectedOutputDataGrid": null,
                "templateRowKey": null,
                "isForDownload": true,
                "isOneDriveTemplate": false,
                "selectedOneDriveFile": null,
                "openInNewTab": true,
                "attachRecord": false,
                "isCurrentUser": false,
                "isCurrentUserOwner": true,
                "isNowTimeValue": false,
                "timeFormat": "HH:mm",
                "isMultiple": false,
                "isAjax": false,
                "dataOptions": [],
                "ajaxDataUrl": "",
                "isChecked": false,
                "vif": "",
                "customCode": "",
                "invisible": false,
                "invisibleCondition": "",
                "invisibleLabel": false,
                "enableCustomValidation": false,
                "customValidationRule": "",
                "customValidationErrorMessage": "",
                "mask": "",
                "lookupOpenInModalDisabled": false,
                "preventModalShowUpWhenNewItemAdded": false,
                "lookUpSearch": null,
                "editorMode": "javascript",
                "dataGridAvailableViews": [],
                "dataGridView": null,
                "dataGridAddRecordsText": "",
                "dataGridAddRecordText": "",
                "skipCrop": false,
                "disableRoundedStyle": false,
                "attachedFunction": "",
                "buttonText": "",
                "buttonVariant": "primary",
                "customClassName": "",
                "propName": "id"
              },
              {
                "type": "number",
                "name": "control_9a232600-3e3c-11f0-bc89-c5ab2e46fbcb",
                "fieldName": "control_9a232600-3e3c-11f0-bc89-c5ab2e46fbcb",
                "label": "item",
                "order": 0,
                "defaultValue": "",
                "value": "",
                "className": "col-md-6",
                "useWidthPercentages": false,
                "widthPercentages": null,
                "readonly": false,
                "readonlyCondition": "",
                "placeholder": "",
                "required": false,
                "requiredCondition": "",
                "isMultiLine": false,
                "isInteger": false,
                "decimalPlace": 2,
                "expression": "",
                "additionalFilter": "",
                "oneDriveFileId": null,
                "isTodayValue": false,
                "isTodayValueCreated": true,
                "dateFormat": "mm/dd/yy hh:mm p",
                "timezone": null,
                "selectedDataGrid": null,
                "printedFileName": null,
                "dataFetchDepth": "basic",
                "buttonLabel": "",
                "dataForTemplate": null,
                "selectedOutputDataGrid": null,
                "templateRowKey": null,
                "isForDownload": true,
                "isOneDriveTemplate": false,
                "selectedOneDriveFile": null,
                "openInNewTab": true,
                "attachRecord": false,
                "isCurrentUser": false,
                "isCurrentUserOwner": true,
                "isNowTimeValue": false,
                "timeFormat": "HH:mm",
                "isMultiple": false,
                "isAjax": false,
                "dataOptions": [],
                "ajaxDataUrl": "",
                "isChecked": false,
                "vif": "",
                "customCode": "",
                "invisible": false,
                "invisibleCondition": "",
                "invisibleLabel": false,
                "enableCustomValidation": false,
                "customValidationRule": "",
                "customValidationErrorMessage": "",
                "mask": "",
                "lookupOpenInModalDisabled": false,
                "preventModalShowUpWhenNewItemAdded": false,
                "lookUpSearch": null,
                "editorMode": "javascript",
                "dataGridAvailableViews": [],
                "dataGridView": null,
                "dataGridAddRecordsText": "",
                "dataGridAddRecordText": "",
                "skipCrop": false,
                "disableRoundedStyle": false,
                "attachedFunction": "",
                "buttonText": "",
                "buttonVariant": "primary",
                "customClassName": "",
                "propName": "item"
              },
              {
                "type": "number",
                "name": "control_9b1dd9b0-3e3c-11f0-bc89-c5ab2e46fbcb",
                "fieldName": "control_9b1dd9b0-3e3c-11f0-bc89-c5ab2e46fbcb",
                "label": "price",
                "order": 0,
                "defaultValue": "",
                "value": "",
                "className": "col-md-6",
                "useWidthPercentages": false,
                "widthPercentages": null,
                "readonly": false,
                "readonlyCondition": "",
                "placeholder": "",
                "required": false,
                "requiredCondition": "",
                "isMultiLine": false,
                "isInteger": false,
                "decimalPlace": 2,
                "expression": "",
                "additionalFilter": "",
                "oneDriveFileId": null,
                "isTodayValue": false,
                "isTodayValueCreated": true,
                "dateFormat": "mm/dd/yy hh:mm p",
                "timezone": null,
                "selectedDataGrid": null,
                "printedFileName": null,
                "dataFetchDepth": "basic",
                "buttonLabel": "",
                "dataForTemplate": null,
                "selectedOutputDataGrid": null,
                "templateRowKey": null,
                "isForDownload": true,
                "isOneDriveTemplate": false,
                "selectedOneDriveFile": null,
                "openInNewTab": true,
                "attachRecord": false,
                "isCurrentUser": false,
                "isCurrentUserOwner": true,
                "isNowTimeValue": false,
                "timeFormat": "HH:mm",
                "isMultiple": false,
                "isAjax": false,
                "dataOptions": [],
                "ajaxDataUrl": "",
                "isChecked": false,
                "vif": "",
                "customCode": "",
                "invisible": false,
                "invisibleCondition": "",
                "invisibleLabel": false,
                "enableCustomValidation": false,
                "customValidationRule": "",
                "customValidationErrorMessage": "",
                "mask": "",
                "lookupOpenInModalDisabled": false,
                "preventModalShowUpWhenNewItemAdded": false,
                "lookUpSearch": null,
                "editorMode": "javascript",
                "dataGridAvailableViews": [],
                "dataGridView": null,
                "dataGridAddRecordsText": "",
                "dataGridAddRecordText": "",
                "skipCrop": false,
                "disableRoundedStyle": false,
                "attachedFunction": "",
                "buttonText": "",
                "buttonVariant": "primary",
                "customClassName": "",
                "propName": "price"
              },
              {
                "type": "number",
                "name": "control_9babc1d0-3e3c-11f0-bc89-c5ab2e46fbcb",
                "fieldName": "control_9babc1d0-3e3c-11f0-bc89-c5ab2e46fbcb",
                "label": "version",
                "order": 0,
                "defaultValue": "",
                "value": "",
                "className": "col-md-6",
                "useWidthPercentages": false,
                "widthPercentages": null,
                "readonly": false,
                "readonlyCondition": "",
                "placeholder": "",
                "required": false,
                "requiredCondition": "",
                "isMultiLine": false,
                "isInteger": false,
                "decimalPlace": 2,
                "expression": "",
                "additionalFilter": "",
                "oneDriveFileId": null,
                "isTodayValue": false,
                "isTodayValueCreated": true,
                "dateFormat": "mm/dd/yy hh:mm p",
                "timezone": null,
                "selectedDataGrid": null,
                "printedFileName": null,
                "dataFetchDepth": "basic",
                "buttonLabel": "",
                "dataForTemplate": null,
                "selectedOutputDataGrid": null,
                "templateRowKey": null,
                "isForDownload": true,
                "isOneDriveTemplate": false,
                "selectedOneDriveFile": null,
                "openInNewTab": true,
                "attachRecord": false,
                "isCurrentUser": false,
                "isCurrentUserOwner": true,
                "isNowTimeValue": false,
                "timeFormat": "HH:mm",
                "isMultiple": false,
                "isAjax": false,
                "dataOptions": [],
                "ajaxDataUrl": "",
                "isChecked": false,
                "vif": "",
                "customCode": "",
                "invisible": false,
                "invisibleCondition": "",
                "invisibleLabel": false,
                "enableCustomValidation": false,
                "customValidationRule": "",
                "customValidationErrorMessage": "",
                "mask": "",
                "lookupOpenInModalDisabled": false,
                "preventModalShowUpWhenNewItemAdded": false,
                "lookUpSearch": null,
                "editorMode": "javascript",
                "dataGridAvailableViews": [],
                "dataGridView": null,
                "dataGridAddRecordsText": "",
                "dataGridAddRecordText": "",
                "skipCrop": false,
                "disableRoundedStyle": false,
                "attachedFunction": "",
                "buttonText": "",
                "buttonVariant": "primary",
                "customClassName": "",
                "propName": "version"
              },
              {
                "type": "number",
                "name": "control_9c3eda10-3e3c-11f0-bc89-c5ab2e46fbcb",
                "fieldName": "control_9c3eda10-3e3c-11f0-bc89-c5ab2e46fbcb",
                "label": "quantity",
                "order": 0,
                "defaultValue": "",
                "value": "",
                "className": "col-md-6",
                "useWidthPercentages": false,
                "widthPercentages": null,
                "readonly": false,
                "readonlyCondition": "",
                "placeholder": "",
                "required": false,
                "requiredCondition": "",
                "isMultiLine": false,
                "isInteger": false,
                "decimalPlace": 2,
                "expression": "",
                "additionalFilter": "",
                "oneDriveFileId": null,
                "isTodayValue": false,
                "isTodayValueCreated": true,
                "dateFormat": "mm/dd/yy hh:mm p",
                "timezone": null,
                "selectedDataGrid": null,
                "printedFileName": null,
                "dataFetchDepth": "basic",
                "buttonLabel": "",
                "dataForTemplate": null,
                "selectedOutputDataGrid": null,
                "templateRowKey": null,
                "isForDownload": true,
                "isOneDriveTemplate": false,
                "selectedOneDriveFile": null,
                "openInNewTab": true,
                "attachRecord": false,
                "isCurrentUser": false,
                "isCurrentUserOwner": true,
                "isNowTimeValue": false,
                "timeFormat": "HH:mm",
                "isMultiple": false,
                "isAjax": false,
                "dataOptions": [],
                "ajaxDataUrl": "",
                "isChecked": false,
                "vif": "",
                "customCode": "",
                "invisible": false,
                "invisibleCondition": "",
                "invisibleLabel": false,
                "enableCustomValidation": false,
                "customValidationRule": "",
                "customValidationErrorMessage": "",
                "mask": "",
                "lookupOpenInModalDisabled": false,
                "preventModalShowUpWhenNewItemAdded": false,
                "lookUpSearch": null,
                "editorMode": "javascript",
                "dataGridAvailableViews": [],
                "dataGridView": null,
                "dataGridAddRecordsText": "",
                "dataGridAddRecordText": "",
                "skipCrop": false,
                "disableRoundedStyle": false,
                "attachedFunction": "",
                "buttonText": "",
                "buttonVariant": "primary",
                "customClassName": "",
                "propName": "quantity"
              },
              {
                "type": "lookup",
                "name": "control_9cbf2da0-3e3c-11f0-bc89-c5ab2e46fbcb",
                "fieldName": "control_9cbf2da0-3e3c-11f0-bc89-c5ab2e46fbcb",
                "label": "pricetype",
                "order": 0,
                "defaultValue": "",
                "value": "",
                "className": "col-md-6",
                "useWidthPercentages": false,
                "widthPercentages": null,
                "readonly": false,
                "readonlyCondition": "",
                "placeholder": "",
                "required": false,
                "requiredCondition": "",
                "isMultiLine": false,
                "isInteger": false,
                "decimalPlace": 2,
                "expression": "",
                "additionalFilter": "",
                "oneDriveFileId": null,
                "isTodayValue": false,
                "isTodayValueCreated": true,
                "dateFormat": "mm/dd/yy hh:mm p",
                "timezone": null,
                "selectedDataGrid": null,
                "printedFileName": null,
                "dataFetchDepth": "basic",
                "buttonLabel": "",
                "dataForTemplate": null,
                "selectedOutputDataGrid": null,
                "templateRowKey": null,
                "isForDownload": true,
                "isOneDriveTemplate": false,
                "selectedOneDriveFile": null,
                "openInNewTab": true,
                "attachRecord": false,
                "isCurrentUser": false,
                "isCurrentUserOwner": true,
                "isNowTimeValue": false,
                "timeFormat": "HH:mm",
                "isMultiple": false,
                "isAjax": false,
                "dataOptions": [],
                "ajaxDataUrl": "",
                "isChecked": false,
                "vif": "",
                "customCode": "",
                "invisible": false,
                "invisibleCondition": "",
                "invisibleLabel": false,
                "enableCustomValidation": false,
                "customValidationRule": "",
                "customValidationErrorMessage": "",
                "mask": "",
                "lookupOpenInModalDisabled": false,
                "preventModalShowUpWhenNewItemAdded": false,
                "lookUpSearch": null,
                "editorMode": "javascript",
                "dataGridAvailableViews": [],
                "dataGridView": null,
                "dataGridAddRecordsText": "",
                "dataGridAddRecordText": "",
                "skipCrop": false,
                "disableRoundedStyle": false,
                "attachedFunction": "",
                "buttonText": "",
                "buttonVariant": "primary",
                "customClassName": "",
                "propName": "pricetype",
                "ableToAddLookUpVal": true
              },
              {
                "type": "number",
                "name": "control_9d819340-3e3c-11f0-bc89-c5ab2e46fbcb",
                "fieldName": "control_9d819340-3e3c-11f0-bc89-c5ab2e46fbcb",
                "label": "internalid",
                "order": 0,
                "defaultValue": "",
                "value": "",
                "className": "col-md-6",
                "useWidthPercentages": false,
                "widthPercentages": null,
                "readonly": false,
                "readonlyCondition": "",
                "placeholder": "",
                "required": false,
                "requiredCondition": "",
                "isMultiLine": false,
                "isInteger": false,
                "decimalPlace": 2,
                "expression": "",
                "additionalFilter": "",
                "oneDriveFileId": null,
                "isTodayValue": false,
                "isTodayValueCreated": true,
                "dateFormat": "mm/dd/yy hh:mm p",
                "timezone": null,
                "selectedDataGrid": null,
                "printedFileName": null,
                "dataFetchDepth": "basic",
                "buttonLabel": "",
                "dataForTemplate": null,
                "selectedOutputDataGrid": null,
                "templateRowKey": null,
                "isForDownload": true,
                "isOneDriveTemplate": false,
                "selectedOneDriveFile": null,
                "openInNewTab": true,
                "attachRecord": false,
                "isCurrentUser": false,
                "isCurrentUserOwner": true,
                "isNowTimeValue": false,
                "timeFormat": "HH:mm",
                "isMultiple": false,
                "isAjax": false,
                "dataOptions": [],
                "ajaxDataUrl": "",
                "isChecked": false,
                "vif": "",
                "customCode": "",
                "invisible": false,
                "invisibleCondition": "",
                "invisibleLabel": false,
                "enableCustomValidation": false,
                "customValidationRule": "",
                "customValidationErrorMessage": "",
                "mask": "",
                "lookupOpenInModalDisabled": false,
                "preventModalShowUpWhenNewItemAdded": false,
                "lookUpSearch": null,
                "editorMode": "javascript",
                "dataGridAvailableViews": [],
                "dataGridView": null,
                "dataGridAddRecordsText": "",
                "dataGridAddRecordText": "",
                "skipCrop": false,
                "disableRoundedStyle": false,
                "attachedFunction": "",
                "buttonText": "",
                "buttonVariant": "primary",
                "customClassName": "",
                "propName": "internalid"
              },
              {
                "type": "number",
                "name": "control_9fc45750-3e3c-11f0-bc89-c5ab2e46fbcb",
                "fieldName": "control_9fc45750-3e3c-11f0-bc89-c5ab2e46fbcb",
                "label": "itemquantityid",
                "order": 0,
                "defaultValue": "",
                "value": "",
                "className": "col-md-6",
                "useWidthPercentages": false,
                "widthPercentages": null,
                "readonly": false,
                "readonlyCondition": "",
                "placeholder": "",
                "required": false,
                "requiredCondition": "",
                "isMultiLine": false,
                "isInteger": false,
                "decimalPlace": 2,
                "expression": "",
                "additionalFilter": "",
                "oneDriveFileId": null,
                "isTodayValue": false,
                "isTodayValueCreated": true,
                "dateFormat": "mm/dd/yy hh:mm p",
                "timezone": null,
                "selectedDataGrid": null,
                "printedFileName": null,
                "dataFetchDepth": "basic",
                "buttonLabel": "",
                "dataForTemplate": null,
                "selectedOutputDataGrid": null,
                "templateRowKey": null,
                "isForDownload": true,
                "isOneDriveTemplate": false,
                "selectedOneDriveFile": null,
                "openInNewTab": true,
                "attachRecord": false,
                "isCurrentUser": false,
                "isCurrentUserOwner": true,
                "isNowTimeValue": false,
                "timeFormat": "HH:mm",
                "isMultiple": false,
                "isAjax": false,
                "dataOptions": [],
                "ajaxDataUrl": "",
                "isChecked": false,
                "vif": "",
                "customCode": "",
                "invisible": false,
                "invisibleCondition": "",
                "invisibleLabel": false,
                "enableCustomValidation": false,
                "customValidationRule": "",
                "customValidationErrorMessage": "",
                "mask": "",
                "lookupOpenInModalDisabled": false,
                "preventModalShowUpWhenNewItemAdded": false,
                "lookUpSearch": null,
                "editorMode": "javascript",
                "dataGridAvailableViews": [],
                "dataGridView": null,
                "dataGridAddRecordsText": "",
                "dataGridAddRecordText": "",
                "skipCrop": false,
                "disableRoundedStyle": false,
                "attachedFunction": "",
                "buttonText": "",
                "buttonVariant": "primary",
                "customClassName": "",
                "propName": "itemquantityid"
              }
            ]
          }
        ],
        "labelPosition": "top",
        "isDynamic": false,
        "minInstance": 1,
        "maxInstance": 0,
        "instances": []
      },
      {
        "cleintKey": "hidden_section_4bd78220-3e3c-11f0-bc89-c5ab2e46fbcb",
        "instances": [],
        "isDynamic": false,
        "label": "Hidden Section",
        "vif": "false",
        "name": "hidden_section_4bd78220-3e3c-11f0-bc89-c5ab2e46fbcb",
        "order": 1,
        "rows": [
          {
            "name": "hidden_section_4bd78220-3e3c-11f0-bc89-c5ab2e46fbcb_row_4bd78221-3e3c-11f0-bc89-c5ab2e46fbcb",
            "controls": [
              {
                "type": "select",
                "name": "control_4c21aa80-3e3c-11f0-bc89-c5ab2e46fbcb",
                "fieldName": "control_4c21aa80-3e3c-11f0-bc89-c5ab2e46fbcb",
                "label": "Layout",
                "order": 0,
                "defaultValue": "",
                "value": "",
                "className": "col-md-6",
                "useWidthPercentages": false,
                "widthPercentages": null,
                "readonly": false,
                "readonlyCondition": "",
                "placeholder": "",
                "required": false,
                "requiredCondition": "",
                "isMultiLine": false,
                "isInteger": false,
                "decimalPlace": 2,
                "expression": "",
                "additionalFilter": "",
                "oneDriveFileId": null,
                "isTodayValue": false,
                "isTodayValueCreated": true,
                "dateFormat": "mm/dd/yy hh:mm p",
                "timezone": null,
                "selectedDataGrid": null,
                "printedFileName": null,
                "dataFetchDepth": "basic",
                "buttonLabel": "",
                "dataForTemplate": null,
                "selectedOutputDataGrid": null,
                "templateRowKey": null,
                "isForDownload": true,
                "isOneDriveTemplate": false,
                "selectedOneDriveFile": null,
                "openInNewTab": true,
                "attachRecord": false,
                "isCurrentUser": false,
                "isCurrentUserOwner": true,
                "isNowTimeValue": false,
                "timeFormat": "HH:mm",
                "isMultiple": false,
                "isAjax": false,
                "dataOptions": [],
                "ajaxDataUrl": "",
                "isChecked": false,
                "vif": "",
                "customCode": "",
                "invisible": true,
                "invisibleCondition": "",
                "invisibleLabel": false,
                "enableCustomValidation": false,
                "customValidationRule": "",
                "customValidationErrorMessage": "",
                "mask": "",
                "lookupOpenInModalDisabled": false,
                "preventModalShowUpWhenNewItemAdded": false,
                "lookUpSearch": null,
                "editorMode": "javascript",
                "dataGridAvailableViews": [],
                "dataGridView": null,
                "dataGridAddRecordsText": "",
                "dataGridAddRecordText": "",
                "skipCrop": false,
                "disableRoundedStyle": false,
                "attachedFunction": "",
                "buttonText": "",
                "buttonVariant": "primary",
                "customClassName": "",
                "propName": "layout"
              },
              {
                "type": "user",
                "name": "control_4c6b5db0-3e3c-11f0-bc89-c5ab2e46fbcb",
                "fieldName": "control_4c6b5db0-3e3c-11f0-bc89-c5ab2e46fbcb",
                "label": "Owner",
                "order": 0,
                "defaultValue": "",
                "value": "",
                "className": "col-md-6",
                "useWidthPercentages": false,
                "widthPercentages": null,
                "readonly": false,
                "readonlyCondition": "",
                "placeholder": "",
                "required": false,
                "requiredCondition": "",
                "isMultiLine": false,
                "isInteger": false,
                "decimalPlace": 2,
                "expression": "",
                "additionalFilter": "",
                "oneDriveFileId": null,
                "isTodayValue": false,
                "isTodayValueCreated": true,
                "dateFormat": "mm/dd/yy hh:mm p",
                "timezone": null,
                "selectedDataGrid": null,
                "printedFileName": null,
                "dataFetchDepth": "basic",
                "buttonLabel": "",
                "dataForTemplate": null,
                "selectedOutputDataGrid": null,
                "templateRowKey": null,
                "isForDownload": true,
                "isOneDriveTemplate": false,
                "selectedOneDriveFile": null,
                "openInNewTab": true,
                "attachRecord": false,
                "isCurrentUser": false,
                "isCurrentUserOwner": true,
                "isNowTimeValue": false,
                "timeFormat": "HH:mm",
                "isMultiple": false,
                "isAjax": false,
                "dataOptions": [],
                "ajaxDataUrl": "",
                "isChecked": false,
                "vif": "",
                "customCode": "",
                "invisible": true,
                "invisibleCondition": "",
                "invisibleLabel": false,
                "enableCustomValidation": false,
                "customValidationRule": "",
                "customValidationErrorMessage": "",
                "mask": "",
                "lookupOpenInModalDisabled": false,
                "preventModalShowUpWhenNewItemAdded": false,
                "lookUpSearch": null,
                "editorMode": "javascript",
                "dataGridAvailableViews": [],
                "dataGridView": null,
                "dataGridAddRecordsText": "",
                "dataGridAddRecordText": "",
                "skipCrop": false,
                "disableRoundedStyle": false,
                "attachedFunction": "",
                "buttonText": "",
                "buttonVariant": "primary",
                "customClassName": "",
                "propName": "owner"
              },
              {
                "type": "datepicker",
                "name": "control_4cb14050-3e3c-11f0-bc89-c5ab2e46fbcb",
                "fieldName": "control_4cb14050-3e3c-11f0-bc89-c5ab2e46fbcb",
                "label": "Created Date",
                "order": 0,
                "defaultValue": "",
                "value": "",
                "className": "col-md-6",
                "useWidthPercentages": false,
                "widthPercentages": null,
                "readonly": false,
                "readonlyCondition": "",
                "placeholder": "",
                "required": false,
                "requiredCondition": "",
                "isMultiLine": false,
                "isInteger": false,
                "decimalPlace": 2,
                "expression": "",
                "additionalFilter": "",
                "oneDriveFileId": null,
                "isTodayValue": false,
                "isTodayValueCreated": true,
                "dateFormat": "mm/dd/yy hh:mm p",
                "timezone": null,
                "selectedDataGrid": null,
                "printedFileName": null,
                "dataFetchDepth": "basic",
                "buttonLabel": "",
                "dataForTemplate": null,
                "selectedOutputDataGrid": null,
                "templateRowKey": null,
                "isForDownload": true,
                "isOneDriveTemplate": false,
                "selectedOneDriveFile": null,
                "openInNewTab": true,
                "attachRecord": false,
                "isCurrentUser": false,
                "isCurrentUserOwner": true,
                "isNowTimeValue": false,
                "timeFormat": "HH:mm",
                "isMultiple": false,
                "isAjax": false,
                "dataOptions": [],
                "ajaxDataUrl": "",
                "isChecked": false,
                "vif": "",
                "customCode": "",
                "invisible": true,
                "invisibleCondition": "",
                "invisibleLabel": false,
                "enableCustomValidation": false,
                "customValidationRule": "",
                "customValidationErrorMessage": "",
                "mask": "",
                "lookupOpenInModalDisabled": false,
                "preventModalShowUpWhenNewItemAdded": false,
                "lookUpSearch": null,
                "editorMode": "javascript",
                "dataGridAvailableViews": [],
                "dataGridView": null,
                "dataGridAddRecordsText": "",
                "dataGridAddRecordText": "",
                "skipCrop": false,
                "disableRoundedStyle": false,
                "attachedFunction": "",
                "buttonText": "",
                "buttonVariant": "primary",
                "customClassName": "",
                "propName": "createdDate"
              },
              {
                "type": "text",
                "name": "control_4cf88280-3e3c-11f0-bc89-c5ab2e46fbcb",
                "fieldName": "control_4cf88280-3e3c-11f0-bc89-c5ab2e46fbcb",
                "label": "State",
                "order": 0,
                "defaultValue": "",
                "value": "",
                "className": "col-md-6",
                "useWidthPercentages": false,
                "widthPercentages": null,
                "readonly": false,
                "readonlyCondition": "",
                "placeholder": "",
                "required": false,
                "requiredCondition": "",
                "isMultiLine": false,
                "isInteger": false,
                "decimalPlace": 2,
                "expression": "",
                "additionalFilter": "",
                "oneDriveFileId": null,
                "isTodayValue": false,
                "isTodayValueCreated": true,
                "dateFormat": "mm/dd/yy hh:mm p",
                "timezone": null,
                "selectedDataGrid": null,
                "printedFileName": null,
                "dataFetchDepth": "basic",
                "buttonLabel": "",
                "dataForTemplate": null,
                "selectedOutputDataGrid": null,
                "templateRowKey": null,
                "isForDownload": true,
                "isOneDriveTemplate": false,
                "selectedOneDriveFile": null,
                "openInNewTab": true,
                "attachRecord": false,
                "isCurrentUser": false,
                "isCurrentUserOwner": true,
                "isNowTimeValue": false,
                "timeFormat": "HH:mm",
                "isMultiple": false,
                "isAjax": false,
                "dataOptions": [],
                "ajaxDataUrl": "",
                "isChecked": false,
                "vif": "",
                "customCode": "",
                "invisible": true,
                "invisibleCondition": "",
                "invisibleLabel": false,
                "enableCustomValidation": false,
                "customValidationRule": "",
                "customValidationErrorMessage": "",
                "mask": "",
                "lookupOpenInModalDisabled": false,
                "preventModalShowUpWhenNewItemAdded": false,
                "lookUpSearch": null,
                "editorMode": "javascript",
                "dataGridAvailableViews": [],
                "dataGridView": null,
                "dataGridAddRecordsText": "",
                "dataGridAddRecordText": "",
                "skipCrop": false,
                "disableRoundedStyle": false,
                "attachedFunction": "",
                "buttonText": "",
                "buttonVariant": "primary",
                "customClassName": "",
                "propName": "state"
              },
              {
                "type": "text",
                "name": "control_4d3f9da0-3e3c-11f0-bc89-c5ab2e46fbcb",
                "fieldName": "control_4d3f9da0-3e3c-11f0-bc89-c5ab2e46fbcb",
                "label": "Next Events",
                "order": 0,
                "defaultValue": "",
                "value": "",
                "className": "col-md-6",
                "useWidthPercentages": false,
                "widthPercentages": null,
                "readonly": false,
                "readonlyCondition": "",
                "placeholder": "",
                "required": false,
                "requiredCondition": "",
                "isMultiLine": false,
                "isInteger": false,
                "decimalPlace": 2,
                "expression": "",
                "additionalFilter": "",
                "oneDriveFileId": null,
                "isTodayValue": false,
                "isTodayValueCreated": true,
                "dateFormat": "mm/dd/yy hh:mm p",
                "timezone": null,
                "selectedDataGrid": null,
                "printedFileName": null,
                "dataFetchDepth": "basic",
                "buttonLabel": "",
                "dataForTemplate": null,
                "selectedOutputDataGrid": null,
                "templateRowKey": null,
                "isForDownload": true,
                "isOneDriveTemplate": false,
                "selectedOneDriveFile": null,
                "openInNewTab": true,
                "attachRecord": false,
                "isCurrentUser": false,
                "isCurrentUserOwner": true,
                "isNowTimeValue": false,
                "timeFormat": "HH:mm",
                "isMultiple": false,
                "isAjax": false,
                "dataOptions": [],
                "ajaxDataUrl": "",
                "isChecked": false,
                "vif": "",
                "customCode": "",
                "invisible": true,
                "invisibleCondition": "",
                "invisibleLabel": false,
                "enableCustomValidation": false,
                "customValidationRule": "",
                "customValidationErrorMessage": "",
                "mask": "",
                "lookupOpenInModalDisabled": false,
                "preventModalShowUpWhenNewItemAdded": false,
                "lookUpSearch": null,
                "editorMode": "javascript",
                "dataGridAvailableViews": [],
                "dataGridView": null,
                "dataGridAddRecordsText": "",
                "dataGridAddRecordText": "",
                "skipCrop": false,
                "disableRoundedStyle": false,
                "attachedFunction": "",
                "buttonText": "",
                "buttonVariant": "primary",
                "customClassName": "",
                "propName": "nextEvents"
              },
              {
                "type": "user",
                "name": "control_4d855930-3e3c-11f0-bc89-c5ab2e46fbcb",
                "fieldName": "control_4d855930-3e3c-11f0-bc89-c5ab2e46fbcb",
                "label": "Last edited by",
                "order": 0,
                "defaultValue": "",
                "value": "",
                "className": "col-md-6",
                "useWidthPercentages": false,
                "widthPercentages": null,
                "readonly": true,
                "readonlyCondition": "",
                "placeholder": "",
                "required": false,
                "requiredCondition": "",
                "isMultiLine": false,
                "isInteger": false,
                "decimalPlace": 2,
                "expression": "",
                "additionalFilter": "",
                "oneDriveFileId": null,
                "isTodayValue": false,
                "isTodayValueCreated": true,
                "dateFormat": "mm/dd/yy hh:mm p",
                "timezone": null,
                "selectedDataGrid": null,
                "printedFileName": null,
                "dataFetchDepth": "basic",
                "buttonLabel": "",
                "dataForTemplate": null,
                "selectedOutputDataGrid": null,
                "templateRowKey": null,
                "isForDownload": true,
                "isOneDriveTemplate": false,
                "selectedOneDriveFile": null,
                "openInNewTab": true,
                "attachRecord": false,
                "isCurrentUser": false,
                "isCurrentUserOwner": true,
                "isNowTimeValue": false,
                "timeFormat": "HH:mm",
                "isMultiple": false,
                "isAjax": false,
                "dataOptions": [],
                "ajaxDataUrl": "",
                "isChecked": false,
                "vif": "",
                "customCode": "",
                "invisible": true,
                "invisibleCondition": "",
                "invisibleLabel": false,
                "enableCustomValidation": false,
                "customValidationRule": "",
                "customValidationErrorMessage": "",
                "mask": "",
                "lookupOpenInModalDisabled": false,
                "preventModalShowUpWhenNewItemAdded": false,
                "lookUpSearch": null,
                "editorMode": "javascript",
                "dataGridAvailableViews": [],
                "dataGridView": null,
                "dataGridAddRecordsText": "",
                "dataGridAddRecordText": "",
                "skipCrop": false,
                "disableRoundedStyle": false,
                "attachedFunction": "",
                "buttonText": "",
                "buttonVariant": "primary",
                "customClassName": "",
                "propName": "lastEditedBy"
              },
              {
                "type": "datepicker",
                "name": "control_4dcaedb0-3e3c-11f0-bc89-c5ab2e46fbcb",
                "fieldName": "control_4dcaedb0-3e3c-11f0-bc89-c5ab2e46fbcb",
                "label": "Last edit date",
                "order": 0,
                "defaultValue": "",
                "value": "",
                "className": "col-md-6",
                "useWidthPercentages": false,
                "widthPercentages": null,
                "readonly": true,
                "readonlyCondition": "",
                "placeholder": "",
                "required": false,
                "requiredCondition": "",
                "isMultiLine": false,
                "isInteger": false,
                "decimalPlace": 2,
                "expression": "",
                "additionalFilter": "",
                "oneDriveFileId": null,
                "isTodayValue": false,
                "isTodayValueCreated": true,
                "dateFormat": "mm/dd/yy hh:mm p",
                "timezone": null,
                "selectedDataGrid": null,
                "printedFileName": null,
                "dataFetchDepth": "basic",
                "buttonLabel": "",
                "dataForTemplate": null,
                "selectedOutputDataGrid": null,
                "templateRowKey": null,
                "isForDownload": true,
                "isOneDriveTemplate": false,
                "selectedOneDriveFile": null,
                "openInNewTab": true,
                "attachRecord": false,
                "isCurrentUser": false,
                "isCurrentUserOwner": true,
                "isNowTimeValue": false,
                "timeFormat": "HH:mm",
                "isMultiple": false,
                "isAjax": false,
                "dataOptions": [],
                "ajaxDataUrl": "",
                "isChecked": false,
                "vif": "",
                "customCode": "",
                "invisible": true,
                "invisibleCondition": "",
                "invisibleLabel": false,
                "enableCustomValidation": false,
                "customValidationRule": "",
                "customValidationErrorMessage": "",
                "mask": "",
                "lookupOpenInModalDisabled": false,
                "preventModalShowUpWhenNewItemAdded": false,
                "lookUpSearch": null,
                "editorMode": "javascript",
                "dataGridAvailableViews": [],
                "dataGridView": null,
                "dataGridAddRecordsText": "",
                "dataGridAddRecordText": "",
                "skipCrop": false,
                "disableRoundedStyle": false,
                "attachedFunction": "",
                "buttonText": "",
                "buttonVariant": "primary",
                "customClassName": "",
                "propName": "lastEditDate"
              }
            ]
          }
        ]
      }
    ],
    "layout": "collapse"
  },
  "source": "pricing",
  "storageType": "dashboard",
  "title": "Pricing"
}